optimize_later/__init__.py
optimize_later/apps.py
optimize_later/config.py
optimize_later/core.py
optimize_later/utils.py
optimize_later/tests/__init__.py
optimize_later/tests/test_django.py
optimize_later/tests/test_standard.py
optimize_later-0.3.dist-info/LICENSE
optimize_later-0.3.dist-info/METADATA
optimize_later-0.3.dist-info/WHEEL
optimize_later-0.3.dist-info/top_level.txt
optimize_later-0.3.dist-info/RECORD
