Metadata-Version: 2.1
Name: optimize-later
Version: 0.3
Summary: Mark potentially slow blocks for notifications when it actually turns out too slow, so you can optimize it.
Home-page: https://github.com/quantum5/optimize-later
Author: Quantum
Author-email: quantum@dmoj.ca
License: MIT
Keywords: optimize profiler speed
Platform: UNKNOWN
Classifier: Development Status :: 3 - Alpha
Classifier: Environment :: Web Environment
Classifier: Framework :: Django
Classifier: Framework :: Django :: 1.11
Classifier: Framework :: Django :: 2.0
Classifier: Framework :: Django :: 2.1
Classifier: Framework :: Django :: 2.2
Classifier: Framework :: Django :: 3.0
Classifier: Intended Audience :: Developers
Classifier: Intended Audience :: System Administrators
Classifier: License :: OSI Approved :: MIT License
Classifier: Operating System :: OS Independent
Classifier: Programming Language :: Python
Classifier: Programming Language :: Python :: 3 :: Only
Classifier: Topic :: Internet :: WWW/HTTP
Classifier: Topic :: Software Development
Classifier: Topic :: Software Development :: Libraries :: Python Modules
